gislib/__init__.py
gislib/clip.py
gislib/version.py
gislib-0.0.1.dist-info/METADATA
gislib-0.0.1.dist-info/WHEEL
gislib-0.0.1.dist-info/top_level.txt
gislib-0.0.1.dist-info/RECORD
